{"cameraMode":{"drawMode":0,"name":"Shaded","section":"Shading Mode"},"sceneLighting":true,"audioPlay":false,"sceneViewState":{"showFog":true,"showMaterialUpdate":false,"showSkybox":true,"showFlares":true,"showImageEffects":true,"showParticleSystems":true},"in2DMode":false,"pivot":{"x":3.6535558700561525,"y":-0.007704026997089386,"z":-11.020258903503418},"rotation":{"x":0.16815343499183656,"y":0.6912758946418762,"z":-0.170491024851799,"w":0.6817834377288818},"size":16.66783332824707,"orthographic":false}